layback/__init__.py
layback/archive.py
layback/cli.py
Layback-0.0.7.dist-info/LICENSE.txt
Layback-0.0.7.dist-info/METADATA
Layback-0.0.7.dist-info/WHEEL
Layback-0.0.7.dist-info/entry_points.txt
Layback-0.0.7.dist-info/top_level.txt
Layback-0.0.7.dist-info/RECORD
