Metadata-Version: 2.1
Name: Layback
Version: 0.0.7
Summary: Creates an animated GIF of a given URLs history.
Home-page: http://github.com/scottmey/layback
Author: Scott Meyers
Author-email: scottmey@gmail.com
License: MIT
Keywords: wayback machine archive mementos
Platform: UNKNOWN
Classifier: Development Status :: 4 - Beta
Classifier: Intended Audience :: Developers
Classifier: License :: OSI Approved :: MIT License
Classifier: Programming Language :: Python :: 3
Requires-Dist: imageio
Requires-Dist: numpy
Requires-Dist: selenium
